hatch_multi/__init__.py
hatch_multi/hooks.py
hatch_multi/plugin.py
hatch_multi/structs.py
hatch_multi/tests/test_projects.py
hatch_multi/tests/test_structs.py
hatch_multi/tests/test_project_basic/pyproject.toml
hatch_multi/tests/test_project_basic/project/__init__.py
hatch_multi-0.1.1.dist-info/METADATA
hatch_multi-0.1.1.dist-info/WHEEL
hatch_multi-0.1.1.dist-info/entry_points.txt
hatch_multi-0.1.1.dist-info/licenses/LICENSE
hatch_multi-0.1.1.dist-info/RECORD
